fine_python_pip/__init__.py
fine_python_pip/install_deps_in_env_handler.py
fine_python_pip-0.1.1.dist-info/METADATA
fine_python_pip-0.1.1.dist-info/WHEEL
fine_python_pip-0.1.1.dist-info/top_level.txt
fine_python_pip-0.1.1.dist-info/RECORD
